reservoirpy/__init__.py
reservoirpy/_version.py
reservoirpy/activationsfunc.py
reservoirpy/esn.py
reservoirpy/mat_gen.py
reservoirpy/model.py
reservoirpy/node.py
reservoirpy/observables.py
reservoirpy/ops.py
reservoirpy/type.py
reservoirpy/datasets/__init__.py
reservoirpy/datasets/_chaos.py
reservoirpy/datasets/_japanese_vowels.py
reservoirpy/datasets/_santafe_laser.py
reservoirpy/datasets/_seed.py
reservoirpy/datasets/_utils.py
reservoirpy/datasets/santafe_laser.npy
reservoirpy/datasets/tests/__init__.py
reservoirpy/datasets/tests/test_datasets.py
reservoirpy/hyper/__init__.py
reservoirpy/hyper/_hyperplot.py
reservoirpy/hyper/_hypersearch.py
reservoirpy/hyper/_parallel_hypersearch.py
reservoirpy/jax/__init__.py
reservoirpy/jax/activationsfunc.py
reservoirpy/jax/esn.py
reservoirpy/jax/mat_gen.py
reservoirpy/jax/model.py
reservoirpy/jax/node.py
reservoirpy/jax/ops.py
reservoirpy/jax/type.py
reservoirpy/jax/utils.py
reservoirpy/jax/nodes/__init__.py
reservoirpy/jax/nodes/activations.py
reservoirpy/jax/nodes/es2n.py
reservoirpy/jax/nodes/intrinsic_plasticity.py
reservoirpy/jax/nodes/io.py
reservoirpy/jax/nodes/lif.py
reservoirpy/jax/nodes/lms.py
reservoirpy/jax/nodes/local_plasticity_reservoir.py
reservoirpy/jax/nodes/nvar.py
reservoirpy/jax/nodes/reservoir.py
reservoirpy/jax/nodes/ridge.py
reservoirpy/jax/nodes/rls.py
reservoirpy/jax/nodes/tests/__init__.py
reservoirpy/jax/nodes/tests/test_es2n.py
reservoirpy/jax/nodes/tests/test_intrinsic_plasticity.py
reservoirpy/jax/nodes/tests/test_io.py
reservoirpy/jax/nodes/tests/test_jax_activations.py
reservoirpy/jax/nodes/tests/test_lif.py
reservoirpy/jax/nodes/tests/test_lms.py
reservoirpy/jax/nodes/tests/test_local_plasticity_reservoir.py
reservoirpy/jax/nodes/tests/test_nvar.py
reservoirpy/jax/nodes/tests/test_reservoir.py
reservoirpy/jax/nodes/tests/test_ridge.py
reservoirpy/jax/nodes/tests/test_rls.py
reservoirpy/jax/tests/__init__.py
reservoirpy/jax/tests/dummy_nodes.py
reservoirpy/jax/tests/test_esn.py
reservoirpy-0.4.1.dist-info/licenses/LICENSE
reservoirpy-0.4.1.dist-info/METADATA
reservoirpy-0.4.1.dist-info/WHEEL
reservoirpy-0.4.1.dist-info/top_level.txt
reservoirpy-0.4.1.dist-info/RECORD
