Metadata-Version: 2.4
Name: reservoirpy
Version: 0.4.1
Summary: A simple and flexible code for Reservoir Computing architectures like Echo State Networks.
Home-page: https://github.com/reservoirpy/reservoirpy
Download-URL: https://github.com/reservoirpy/reservoirpy/v0.4.1.tar.gz
Author: Xavier Hinaut
Author-email: xavier.hinaut@inria.fr
Maintainer: Xavier Hinaut, Paul Bernard
Maintainer-email: xavier.hinaut@inria.fr, paul.bernard@inria.fr
Project-URL: Bug Tracker, https://github.com/reservoirpy/reservoirpy/issues
Project-URL: Documentation, https://reservoirpy.readthedocs.io/en/latest/index.html
Project-URL: Source Code, https://github.com/reservoirpy/reservoirpy
Project-URL: Release notes, https://github.com/reservoirpy/reservoirpy/releases
Classifier: Intended Audience :: Science/Research
Classifier: Intended Audience :: Developers
Classifier: License :: OSI Approved :: MIT License
Classifier: Programming Language :: Python
Classifier: Topic :: Scientific/Engineering
Classifier: Topic :: Scientific/Engineering :: Artificial Intelligence
Classifier: Operating System :: Microsoft :: Windows
Classifier: Operating System :: POSIX
Classifier: Operating System :: Unix
Classifier: Operating System :: MacOS
Classifier: Operating System :: OS Independent
Classifier: Programming Language :: Python :: 3
Classifier: Programming Language :: Python :: 3.9
Classifier: Programming Language :: Python :: 3.10
Classifier: Programming Language :: Python :: 3.11
Classifier: Programming Language :: Python :: 3.12
Classifier: Programming Language :: Python :: 3.13
Classifier: Programming Language :: Python :: Implementation :: PyPy
Requires-Python: >=3.9
License-File: LICENSE
Requires-Dist: joblib>=0.14.1
Requires-Dist: numpy>=1.21.1
Requires-Dist: scipy>=1.4.1
Provides-Extra: hyper
Requires-Dist: hyperopt; extra == "hyper"
Requires-Dist: matplotlib>=2.2.0; extra == "hyper"
Requires-Dist: tqdm>=4.43.0; extra == "hyper"
Provides-Extra: sklearn
Requires-Dist: scikit-learn<1.7.0,>=0.24.2; extra == "sklearn"
Provides-Extra: jax
Requires-Dist: jax==0.7.1; extra == "jax"
Provides-Extra: all
Requires-Dist: hyperopt; extra == "all"
Requires-Dist: matplotlib>=2.2.0; extra == "all"
Requires-Dist: tqdm>=4.43.0; extra == "all"
Requires-Dist: scikit-learn>=0.24.2; extra == "all"
Requires-Dist: jax==0.7.1; extra == "all"
Dynamic: author
Dynamic: author-email
Dynamic: classifier
Dynamic: description
Dynamic: description-content-type
Dynamic: download-url
Dynamic: home-page
Dynamic: license-file
Dynamic: maintainer
Dynamic: maintainer-email
Dynamic: project-url
Dynamic: provides-extra
Dynamic: requires-dist
Dynamic: requires-python
Dynamic: summary
